<?xml version="1.0" encoding="UTF-8"?>
<ehcache xmlns:xsi="http://www.w3.org/2001/XMLSchema-instance" xsi:noNamespaceSchemaLocation="http://ehcache.org/ehcache.xsd"
		 updateCheck="false" monitoring="autodetect" dynamicConfig="true">

	<defaultCache eternal="true" maxElementsInMemory="100" overflowToDisk="false"/>

	<cache name="totalizator.app.cache.category"
		   maxElementsInMemory="300"
		   eternal="true"
		   memoryStoreEvictionPolicy="LRU"
	/>

	<cache name="totalizator.app.cache.categories"
		   maxElementsInMemory="300"
		   eternal="true"
		   memoryStoreEvictionPolicy="LRU"
	/>

	<cache name="totalizator.app.cache.cup"
		   maxElementsInMemory="300"
		   eternal="true"
		   memoryStoreEvictionPolicy="LRU"
	/>

	<cache name="totalizator.app.cache.cups"
		   maxElementsInMemory="300"
		   eternal="true"
		   memoryStoreEvictionPolicy="LRU"
	/>

	<cache name="totalizator.app.cache.user-cup-winner-bet"
		   maxElementsInMemory="300"
		   eternal="true"
		   memoryStoreEvictionPolicy="LRU"
	/>

	<cache name="totalizator.app.cache.user-cup-winner-bet.query"
		   maxElementsInMemory="300"
		   eternal="true"
		   memoryStoreEvictionPolicy="LRU"
	/>

	<cache name="totalizator.app.cache.cup-winner"
		   maxElementsInMemory="300"
		   eternal="true"
		   memoryStoreEvictionPolicy="LRU"
	/>

	<cache name="totalizator.app.cache.cup-winner.query"
		   maxElementsInMemory="300"
		   eternal="true"
		   memoryStoreEvictionPolicy="LRU"
	/>

	<cache name="totalizator.app.cache.match-bet"
		   maxElementsInMemory="1000"
		   eternal="true"
		   memoryStoreEvictionPolicy="LRU"
	/>

	<cache name="totalizator.app.cache.match-bet.query"
		   maxElementsInMemory="1000"
		   eternal="true"
		   memoryStoreEvictionPolicy="LRU"
	/>

	<cache name="totalizator.app.cache.match"
		   maxElementsInMemory="1000"
		   eternal="true"
		   memoryStoreEvictionPolicy="LRU"
	/>

	<cache name="totalizator.app.cache.matches"
		   maxElementsInMemory="1000"
		   eternal="true"
		   memoryStoreEvictionPolicy="LRU"
	/>

	<cache name="totalizator.app.cache.team"
		   maxElementsInMemory="2000"
		   eternal="true"
		   memoryStoreEvictionPolicy="LRU"
	/>

	<cache name="totalizator.app.cache.teams"
		   maxElementsInMemory="2000"
		   eternal="true"
		   memoryStoreEvictionPolicy="LRU"
	/>

	<cache name="totalizator.app.cache.user"
		   maxElementsInMemory="1000"
		   eternal="true"
		   memoryStoreEvictionPolicy="LRU"
	/>

	<cache name="totalizator.app.cache.users"
		   maxElementsInMemory="1000"
		   eternal="true"
		   memoryStoreEvictionPolicy="LRU"
	/>

	<cache name="totalizator.app.cache.user-bet-points-calculation.query"
		   maxElementsInMemory="1000"
		   eternal="true"
		   memoryStoreEvictionPolicy="LRU"
	/>

	<cache name="totalizator.app.cache.user-match-points-calculation.query"
		   maxElementsInMemory="1000"
		   eternal="true"
		   memoryStoreEvictionPolicy="LRU"
	/>

	<cache name="totalizator.app.cache.user-match-bonus-points-calculation.query"
		   maxElementsInMemory="1000"
		   eternal="true"
		   memoryStoreEvictionPolicy="LRU"
	/>

	<cache name="totalizator.app.cache.cup-bet-points-calculation.query"
		   maxElementsInMemory="1000"
		   eternal="true"
		   memoryStoreEvictionPolicy="LRU"
	/>

	<cache name="totalizator.app.cache.user-group"
		   maxElementsInMemory="300"
		   eternal="true"
		   memoryStoreEvictionPolicy="LRU"
	/>

	<cache name="totalizator.app.cache.user-group.query"
		   maxElementsInMemory="300"
		   eternal="true"
		   memoryStoreEvictionPolicy="LRU"
	/>

	<cache name="totalizator.app.cache.points-calculation-strategy"
		   maxElementsInMemory="300"
		   eternal="true"
		   memoryStoreEvictionPolicy="LRU"
	/>

	<cache name="totalizator.app.cache.points-calculation-strategy.query"
		   maxElementsInMemory="300"
		   eternal="true"
		   memoryStoreEvictionPolicy="LRU"
	/>

</ehcache>